fbad-0.1.4.dist-info/metadata.json
fbad-0.1.4.dist-info/entry_points.txt
fbad-0.1.4.dist-info/DESCRIPTION.rst
fbad-0.1.4.dist-info/WHEEL
fbad-0.1.4.dist-info/METADATA
fbad-0.1.4.dist-info/top_level.txt
fbad-0.1.4.dist-info/RECORD
fbad/constants.py
fbad/client.py
fbad/image.py
fbad/server.py
fbad/errors.py
fbad/dockerutils.py
fbad/project.py
fbad/shutils.py
fbad/runner.py
fbad/__init__.py
