Metadata-Version: 2.0
Name: fbad
Version: 0.1.4
Summary: build tools for docker images
Home-page: https://github.com/bennr01/fbad/
Author: bennr01
Author-email: benjamin99.vogt@web.de
License: MIT
Keywords: docker build tools
Platform: UNKNOWN
Classifier: License :: OSI Approved :: MIT License
Classifier: Topic :: Software Development :: Build Tools
Classifier: Programming Language :: Python
Classifier: Development Status :: 3 - Alpha
Classifier: Programming Language :: Python :: 2.6
Classifier: Programming Language :: Python :: 2.7
Requires-Dist: twisted
